{
  "extends": "tslint-eslint-rules",
  "rules": {
    "handle-callback-err": [true, "error"],
    "no-constant-condition": true,
    "no-control-regex": true,
    "no-duplicate-case": true,
    "no-empty-character-class": true,
    "no-ex-assign": true,
    "no-extra-boolean-cast": true,
    "no-extra-semi": true,
    "no-inner-declarations": [true, "both"],
    "no-invalid-regexp": true,
    "no-regex-spaces": true,
    "no-unexpected-multiline": true,
    "sort-imports": [
      true,
      {
        "ignore-case": true
      }
    ],
    "ter-arrow-body-style": [
      true,
      "as-needed",
      {
        "requireReturnForObjectLiteral": true
      }
    ],
    "ter-newline-after-var": [true],
    "ter-no-proto": true,
    "ter-no-self-compare": true,
    "ter-no-script-url": true,
    "ter-prefer-arrow-callback": [true],
    "valid-jsdoc": [
      true,
      {
        "requireReturn": false,
        "requireParamDescription": true,
        "requireReturnDescription": true,
        "matchDescription": "^[A-Z][A-Za-z0-9\\s]*[.]$"
      }
    ],
    "valid-typeof": true
  }
}
